testit_adapter_behave
