Metadata-Version: 2.4
Name: testit-adapter-behave
Version: 3.11.1
Summary: Behave adapter for Test IT
Home-page: https://github.com/testit-tms/adapters-python/
Author: Integration team
Author-email: integrations@testit.software
License: Apache-2.0
Classifier: Programming Language :: Python :: 3
Classifier: Programming Language :: Python :: 3.6
Classifier: Programming Language :: Python :: 3.7
Classifier: Programming Language :: Python :: 3.8
Classifier: Programming Language :: Python :: 3.9
Classifier: Programming Language :: Python :: 3.10
Classifier: Programming Language :: Python :: 3.11
Classifier: Programming Language :: Python :: 3.12
Requires-Dist: behave
Requires-Dist: testit-python-commons==3.11.1
Requires-Dist: attrs
Dynamic: author
Dynamic: author-email
Dynamic: classifier
Dynamic: description
Dynamic: description-content-type
Dynamic: home-page
Dynamic: license
Dynamic: requires-dist
Dynamic: summary
